{
  "records": [
    {
      "timestamp": "2026-03-27 23:39:52",
      "entries": [
        {
          "value": "s143",
          "gear": 4,
          "star": "3星",
          "type": "s",
          "order": 1
        },
        {
          "value": "g7",
          "gear": 1,
          "star": "3星",
          "type": "g",
          "order": 2
        },
        {
          "value": "c27",
          "gear": 1,
          "star": "3星",
          "type": "c",
          "order": 3
        },
        {
          "value": "b39",
          "gear": 4,
          "star": "5星",
          "type": "b",
          "order": 4
        },
        {
          "value": "F35",
          "gear": 2,
          "star": "3星",
          "type": "F",
          "order": 5
        },
        {
          "value": "G25",
          "gear": 1,
          "star": "3星",
          "type": "G",
          "order": 6
        },
        {
          "value": "s100",
          "gear": 1,
          "star": "3星",
          "type": "s",
          "order": 7
        },
        {
          "value": "G25",
          "gear": 1,
          "star": "3星",
          "type": "G",
          "order": 8
        },
        {
          "value": "G28",
          "gear": 2,
          "star": "3星",
          "type": "G",
          "order": 9
        },
        {
          "value": "S28",
          "gear": 2,
          "star": "3星",
          "type": "S",
          "order": 10
        },
        {
          "value": "c35",
          "gear": 3,
          "star": "3星",
          "type": "c",
          "order": 11
        },
        {
          "value": "j10",
          "gear": 1,
          "star": "3星",
          "type": "j",
          "order": 12
        },
        {
          "value": "j10",
          "gear": 1,
          "star": "3星",
          "type": "j",
          "order": 13
        },
        {
          "value": "f8",
          "gear": 1,
          "star": "3星",
          "type": "f",
          "order": 14
        },
        {
          "value": "S35",
          "gear": 4,
          "star": "3星",
          "type": "S",
          "order": 15
        },
        {
          "value": "g9",
          "gear": 3,
          "star": "3星",
          "type": "g",
          "order": 16
        },
        {
          "value": "c39",
          "gear": 4,
          "star": "3星",
          "type": "c",
          "order": 17
        },
        {
          "value": "b16",
          "gear": 1,
          "star": "3星",
          "type": "b",
          "order": 18
        },
        {
          "value": "S32",
          "gear": 3,
          "star": "3星",
          "type": "S",
          "order": 19
        },
        {
          "value": "j11",
          "gear": 2,
          "star": "3星",
          "type": "j",
          "order": 20
        },
        {
          "value": "f8",
          "gear": 1,
          "star": "3星",
          "type": "f",
          "order": 21
        },
        {
          "value": "j11",
          "gear": 2,
          "star": "3星",
          "type": "j",
          "order": 22
        },
        {
          "value": "G32",
          "gear": 3,
          "star": "3星",
          "type": "G",
          "order": 23
        },
        {
          "value": "S28",
          "gear": 2,
          "star": "3星",
          "type": "S",
          "order": 24
        },
        {
          "value": "F35",
          "gear": 2,
          "star": "3星",
          "type": "F",
          "order": 25
        },
        {
          "value": "s115",
          "gear": 2,
          "star": "3星",
          "type": "s",
          "order": 26
        },
        {
          "value": "g9",
          "gear": 3,
          "star": "3星",
          "type": "g",
          "order": 27
        },
        {
          "value": "f10",
          "gear": 3,
          "star": "3星",
          "type": "f",
          "order": 28
        },
        {
          "value": "s100",
          "gear": 1,
          "star": "3星",
          "type": "s",
          "order": 29
        },
        {
          "value": "S25",
          "gear": 1,
          "star": "3星",
          "type": "S",
          "order": 30
        },
        {
          "value": "b19",
          "gear": 2,
          "star": "3星",
          "type": "b",
          "order": 31
        },
        {
          "value": "S25",
          "gear": 1,
          "star": "3星",
          "type": "S",
          "order": 32
        },
        {
          "value": "c35",
          "gear": 3,
          "star": "3星",
          "type": "c",
          "order": 33
        },
        {
          "value": "f8",
          "gear": 1,
          "star": "3星",
          "type": "f",
          "order": 34
        },
        {
          "value": "F39",
          "gear": 3,
          "star": "3星",
          "type": "F",
          "order": 35
        },
        {
          "value": "g7",
          "gear": 1,
          "star": "3星",
          "type": "g",
          "order": 36
        },
        {
          "value": "G25",
          "gear": 1,
          "star": "3星",
          "type": "G",
          "order": 37
        },
        {
          "value": "g7",
          "gear": 1,
          "star": "3星",
          "type": "g",
          "order": 38
        },
        {
          "value": "j14",
          "gear": 4,
          "star": "3星",
          "type": "j",
          "order": 39
        },
        {
          "value": "s100",
          "gear": 1,
          "star": "3星",
          "type": "s",
          "order": 40
        },
        {
          "value": "B33",
          "gear": 1,
          "star": "3星",
          "type": "B",
          "order": 41
        },
        {
          "value": "g8",
          "gear": 2,
          "star": "3星",
          "type": "g",
          "order": 42
        },
        {
          "value": "j11",
          "gear": 2,
          "star": "3星",
          "type": "j",
          "order": 43
        },
        {
          "value": "g9",
          "gear": 3,
          "star": "3星",
          "type": "g",
          "order": 44
        },
        {
          "value": "f10",
          "gear": 3,
          "star": "3星",
          "type": "f",
          "order": 45
        },
        {
          "value": "f8",
          "gear": 1,
          "star": "3星",
          "type": "f",
          "order": 46
        },
        {
          "value": "S25",
          "gear": 1,
          "star": "3星",
          "type": "S",
          "order": 47
        },
        {
          "value": "g7",
          "gear": 1,
          "star": "3星",
          "type": "g",
          "order": 48
        },
        {
          "value": "s115",
          "gear": 2,
          "star": "3星",
          "type": "s",
          "order": 49
        },
        {
          "value": "f11",
          "gear": 4,
          "star": "3星",
          "type": "f",
          "order": 50
        },
        {
          "value": "j11",
          "gear": 2,
          "star": "3星",
          "type": "j",
          "order": 51
        },
        {
          "value": "F35",
          "gear": 2,
          "star": "3星",
          "type": "F",
          "order": 52
        },
        {
          "value": "j11",
          "gear": 2,
          "star": "3星",
          "type": "j",
          "order": 53
        },
        {
          "value": "f10",
          "gear": 3,
          "star": "3星",
          "type": "f",
          "order": 54
        },
        {
          "value": "g7",
          "gear": 1,
          "star": "3星",
          "type": "g",
          "order": 55
        },
        {
          "value": "B37",
          "gear": 2,
          "star": "3星",
          "type": "B",
          "order": 56
        },
        {
          "value": "g7",
          "gear": 1,
          "star": "3星",
          "type": "g",
          "order": 57
        },
        {
          "value": "j11",
          "gear": 2,
          "star": "3星",
          "type": "j",
          "order": 58
        },
        {
          "value": "f8",
          "gear": 1,
          "star": "3星",
          "type": "f",
          "order": 59
        },
        {
          "value": "B47",
          "gear": 4,
          "star": "3星",
          "type": "B",
          "order": 60
        },
        {
          "value": "f11",
          "gear": 4,
          "star": "3星",
          "type": "f",
          "order": 61
        },
        {
          "value": "j19",
          "gear": 2,
          "star": "5星",
          "type": "j",
          "order": 62
        },
        {
          "value": "j13",
          "gear": 3,
          "star": "3星",
          "type": "j",
          "order": 63
        },
        {
          "value": "S32",
          "gear": 3,
          "star": "3星",
          "type": "S",
          "order": 64
        },
        {
          "value": "S35",
          "gear": 4,
          "star": "3星",
          "type": "S",
          "order": 65
        },
        {
          "value": "F31",
          "gear": 1,
          "star": "3星",
          "type": "F",
          "order": 66
        },
        {
          "value": "j10",
          "gear": 1,
          "star": "3星",
          "type": "j",
          "order": 67
        },
        {
          "value": "f10",
          "gear": 3,
          "star": "3星",
          "type": "f",
          "order": 68
        },
        {
          "value": "B37",
          "gear": 2,
          "star": "3星",
          "type": "B",
          "order": 69
        },
        {
          "value": "f11",
          "gear": 4,
          "star": "3星",
          "type": "f",
          "order": 70
        },
        {
          "value": "S25",
          "gear": 1,
          "star": "3星",
          "type": "S",
          "order": 71
        },
        {
          "value": "F39",
          "gear": 3,
          "star": "3星",
          "type": "F",
          "order": 72
        },
        {
          "value": "j13",
          "gear": 3,
          "star": "3星",
          "type": "j",
          "order": 73
        },
        {
          "value": "G25",
          "gear": 1,
          "star": "3星",
          "type": "G",
          "order": 74
        },
        {
          "value": "f9",
          "gear": 2,
          "star": "3星",
          "type": "f",
          "order": 75
        },
        {
          "value": "F44",
          "gear": 4,
          "star": "3星",
          "type": "F",
          "order": 76
        },
        {
          "value": "c27",
          "gear": 1,
          "star": "3星",
          "type": "c",
          "order": 77
        },
        {
          "value": "S35",
          "gear": 4,
          "star": "3星",
          "type": "S",
          "order": 78
        },
        {
          "value": "F35",
          "gear": 2,
          "star": "3星",
          "type": "F",
          "order": 79
        },
        {
          "value": "c27",
          "gear": 1,
          "star": "3星",
          "type": "c",
          "order": 80
        },
        {
          "value": "B42",
          "gear": 3,
          "star": "3星",
          "type": "B",
          "order": 81
        },
        {
          "value": "S28",
          "gear": 2,
          "star": "3星",
          "type": "S",
          "order": 82
        },
        {
          "value": "g7",
          "gear": 1,
          "star": "3星",
          "type": "g",
          "order": 83
        },
        {
          "value": "b16",
          "gear": 1,
          "star": "3星",
          "type": "b",
          "order": 84
        },
        {
          "value": "G28",
          "gear": 2,
          "star": "3星",
          "type": "G",
          "order": 85
        },
        {
          "value": "j21",
          "gear": 3,
          "star": "5星",
          "type": "j",
          "order": 86
        },
        {
          "value": "g8",
          "gear": 2,
          "star": "3星",
          "type": "g",
          "order": 87
        },
        {
          "value": "c27",
          "gear": 1,
          "star": "3星",
          "type": "c",
          "order": 88
        },
        {
          "value": "G35",
          "gear": 4,
          "star": "3星",
          "type": "G",
          "order": 89
        },
        {
          "value": "g9",
          "gear": 3,
          "star": "3星",
          "type": "g",
          "order": 90
        },
        {
          "value": "s129",
          "gear": 3,
          "star": "3星",
          "type": "s",
          "order": 91
        },
        {
          "value": "s143",
          "gear": 4,
          "star": "3星",
          "type": "s",
          "order": 92
        },
        {
          "value": "f9",
          "gear": 2,
          "star": "3星",
          "type": "f",
          "order": 93
        },
        {
          "value": "j10",
          "gear": 1,
          "star": "3星",
          "type": "j",
          "order": 94
        },
        {
          "value": "c39",
          "gear": 4,
          "star": "3星",
          "type": "c",
          "order": 95
        },
        {
          "value": "F35",
          "gear": 2,
          "star": "3星",
          "type": "F",
          "order": 96
        },
        {
          "value": "S32",
          "gear": 3,
          "star": "3星",
          "type": "S",
          "order": 97
        },
        {
          "value": "s129",
          "gear": 3,
          "star": "3星",
          "type": "s",
          "order": 98
        },
        {
          "value": "b16",
          "gear": 1,
          "star": "3星",
          "type": "b",
          "order": 99
        },
        {
          "value": "f8",
          "gear": 1,
          "star": "3星",
          "type": "f",
          "order": 100
        },
        {
          "value": "B33",
          "gear": 1,
          "star": "3星",
          "type": "B",
          "order": 101
        },
        {
          "value": "b23",
          "gear": 4,
          "star": "3星",
          "type": "b",
          "order": 102
        },
        {
          "value": "G35",
          "gear": 4,
          "star": "3星",
          "type": "G",
          "order": 103
        },
        {
          "value": "g8",
          "gear": 2,
          "star": "3星",
          "type": "g",
          "order": 104
        },
        {
          "value": "c27",
          "gear": 1,
          "star": "3星",
          "type": "c",
          "order": 105
        },
        {
          "value": "g9",
          "gear": 3,
          "star": "3星",
          "type": "g",
          "order": 106
        },
        {
          "value": "g7",
          "gear": 1,
          "star": "3星",
          "type": "g",
          "order": 107
        },
        {
          "value": "S35",
          "gear": 4,
          "star": "3星",
          "type": "S",
          "order": 108
        },
        {
          "value": "G32",
          "gear": 3,
          "star": "3星",
          "type": "G",
          "order": 109
        },
        {
          "value": "g9",
          "gear": 3,
          "star": "3星",
          "type": "g",
          "order": 110
        },
        {
          "value": "f10",
          "gear": 3,
          "star": "3星",
          "type": "f",
          "order": 111
        },
        {
          "value": "g9",
          "gear": 3,
          "star": "3星",
          "type": "g",
          "order": 112
        },
        {
          "value": "b23",
          "gear": 4,
          "star": "3星",
          "type": "b",
          "order": 113
        },
        {
          "value": "j14",
          "gear": 4,
          "star": "3星",
          "type": "j",
          "order": 114
        },
        {
          "value": "f8",
          "gear": 1,
          "star": "3星",
          "type": "f",
          "order": 115
        },
        {
          "value": "c31",
          "gear": 2,
          "star": "3星",
          "type": "c",
          "order": 116
        },
        {
          "value": "S35",
          "gear": 4,
          "star": "3星",
          "type": "S",
          "order": 117
        },
        {
          "value": "f8",
          "gear": 1,
          "star": "3星",
          "type": "f",
          "order": 118
        },
        {
          "value": "c35",
          "gear": 3,
          "star": "3星",
          "type": "c",
          "order": 119
        },
        {
          "value": "j10",
          "gear": 1,
          "star": "3星",
          "type": "j",
          "order": 120
        },
        {
          "value": "S25",
          "gear": 1,
          "star": "3星",
          "type": "S",
          "order": 121
        },
        {
          "value": "g7",
          "gear": 1,
          "star": "3星",
          "type": "g",
          "order": 122
        },
        {
          "value": "s115",
          "gear": 2,
          "star": "3星",
          "type": "s",
          "order": 123
        },
        {
          "value": "g8",
          "gear": 2,
          "star": "3星",
          "type": "g",
          "order": 124
        },
        {
          "value": "G32",
          "gear": 3,
          "star": "3星",
          "type": "G",
          "order": 125
        },
        {
          "value": "b16",
          "gear": 1,
          "star": "3星",
          "type": "b",
          "order": 126
        },
        {
          "value": "j19",
          "gear": 2,
          "star": "5星",
          "type": "j",
          "order": 127
        },
        {
          "value": "f9",
          "gear": 2,
          "star": "3星",
          "type": "f",
          "order": 128
        },
        {
          "value": "F35",
          "gear": 2,
          "star": "3星",
          "type": "F",
          "order": 129
        },
        {
          "value": "c31",
          "gear": 2,
          "star": "3星",
          "type": "c",
          "order": 130
        },
        {
          "value": "s143",
          "gear": 4,
          "star": "3星",
          "type": "s",
          "order": 131
        },
        {
          "value": "g9",
          "gear": 3,
          "star": "3星",
          "type": "g",
          "order": 132
        },
        {
          "value": "S35",
          "gear": 4,
          "star": "3星",
          "type": "S",
          "order": 133
        },
        {
          "value": "j13",
          "gear": 3,
          "star": "3星",
          "type": "j",
          "order": 134
        },
        {
          "value": "g9",
          "gear": 3,
          "star": "3星",
          "type": "g",
          "order": 135
        },
        {
          "value": "c35",
          "gear": 3,
          "star": "3星",
          "type": "c",
          "order": 136
        },
        {
          "value": "G28",
          "gear": 2,
          "star": "3星",
          "type": "G",
          "order": 137
        },
        {
          "value": "b16",
          "gear": 1,
          "star": "3星",
          "type": "b",
          "order": 138
        },
        {
          "value": "s143",
          "gear": 4,
          "star": "3星",
          "type": "s",
          "order": 139
        },
        {
          "value": "g8",
          "gear": 2,
          "star": "3星",
          "type": "g",
          "order": 140
        },
        {
          "value": "g7",
          "gear": 1,
          "star": "3星",
          "type": "g",
          "order": 141
        },
        {
          "value": "j11",
          "gear": 2,
          "star": "3星",
          "type": "j",
          "order": 142
        },
        {
          "value": "B47",
          "gear": 4,
          "star": "3星",
          "type": "B",
          "order": 143
        },
        {
          "value": "g7",
          "gear": 1,
          "star": "3星",
          "type": "g",
          "order": 144
        },
        {
          "value": "b16",
          "gear": 1,
          "star": "3星",
          "type": "b",
          "order": 145
        },
        {
          "value": "F31",
          "gear": 1,
          "star": "3星",
          "type": "F",
          "order": 146
        },
        {
          "value": "s143",
          "gear": 4,
          "star": "3星",
          "type": "s",
          "order": 147
        },
        {
          "value": "f11",
          "gear": 4,
          "star": "3星",
          "type": "f",
          "order": 148
        },
        {
          "value": "g18",
          "gear": 3,
          "star": "5星",
          "type": "g",
          "order": 149
        }
      ],
      "artifact_type": ""
    }
  ],
  "metadata": {
    "total_records": 1,
    "last_updated": "2026-03-27 23:39:52"
  }
}